tokyo/__init__.py
tokyo/grid.py
tokyo-0.0.1.dist-info/licenses/LICENSE
tokyo-0.0.1.dist-info/METADATA
tokyo-0.0.1.dist-info/WHEEL
tokyo-0.0.1.dist-info/top_level.txt
tokyo-0.0.1.dist-info/RECORD
