Metadata-Version: 2.4
Name: tokyo
Version: 0.0.1
Summary: Tokyo - an sdl project
Author-email: Sinan ISLEKDEMIR <sinan@islekdemir.com>
License-Expression: BSD-3-Clause
Project-URL: Homepage, https://github.com/sinanislekdemir/tokyo
Project-URL: Issues, https://github.com/sinanislekdemir/tokyo/issues
Classifier: Programming Language :: Python :: 3
Classifier: Operating System :: OS Independent
Requires-Python: >=3.12
License-File: LICENSE
Requires-Dist: pysdl2>=0.9.17
Dynamic: license-file
